Metadata-Version: 1.1
Name: lancaster
Version: 0.3.4
Summary: A python extension wrapper for avro-c
Home-page: https://github.com/twosigma/lancaster
Author: Leif Walsh
Author-email: leif@twosigma.com
License: MIT
Download-URL: https://github.com/twosigma/lancaster/tarball/0.3.4
Platform: UNKNOWN
